ARflames
