Metadata-Version: 2.1
Name: ARflames
Version: 1.0.2
Summary: This is fun Games Package for FLAMES Game
Home-page: https://pypi.org/user/ARRM03/
Author: Abdurrahim
Author-email: ar.rahimdeve7418@gmail.com
License: MIT
Project-URL: Source Code, https://github.com/ARRahim7418/Python-Packages.git
Project-URL: Documentation, https://github.com/ARRahim7418/Python-Packages.git
Keywords: FLAMES Game,Games,String,GUI
Classifier: Programming Language :: Python :: 3
Classifier: License :: OSI Approved :: MIT License
Classifier: Operating System :: OS Independent
License-File: License.txt
Requires-Dist: Rahimcalc
Requires-Dist: pillow
